[
  {
    "id": "giant_squid",
    "name_ko": "대왕오징어",
    "name_en": "Giant Squid",
    "scientific_name": "Architeuthis dux",
    "greeting_ko": "안녕! 나는 대왕오징어야!",
    "greeting_en": "Hi! I'm a giant squid!",
    "greeting_revisit_ko": "또 만났구나! 신기하지?",
    "description_ko": "나는 매우 커! 긴 다리와 큰 눈을 가졌어. 어두운 바다에서 살지만 가끔 수면으로 올라와.",
    "description_en": "I'm huge with giant eyes!",
    "fun_fact_ko": "대왕오징어의 눈은 농구공만큼 커. 어둠 속에서 빛을 잘 볼 수 있어!",
    "size_cm": 1200,
    "depth_min": 200,
    "depth_max": 1000,
    "zone": "twilight",
    "oceans": [
      "pacific",
      "atlantic",
      "indian"
    ],
    "seasons": [
      "spring",
      "summer",
      "fall",
      "winter"
    ],
    "rarity": "legendary",
    "diet": "물고기, 작은 오징어",
    "animation_type": "jet",
    "svg_id": "giant_squid",
    "source": "NOAA",
    "photo_url": "",
    "photo_credit": ""
  },
  {
    "id": "hatchetfish",
    "name_ko": "도끼고기",
    "name_en": "Hatchetfish",
    "scientific_name": "Argyropelecus gigas",
    "greeting_ko": "안녕! 나는 도끼고기야!",
    "greeting_en": "Hi! I'm a hatchetfish!",
    "greeting_revisit_ko": "다시 만났네!",
    "description_ko": "내 몸은 도끼처럼 얇아. 배에서 빛이 나서 그림자를 숨겨. 큰 눈으로 먹이를 찾아!",
    "description_en": "My body glows to hide my shadow!",
    "fun_fact_ko": "도끼고기는 위를 쳐다보며 먹이를 찾아. 빛을 내서 위장해!",
    "size_cm": 12,
    "depth_min": 200,
    "depth_max": 600,
    "zone": "twilight",
    "oceans": [
      "pacific",
      "atlantic",
      "indian"
    ],
    "seasons": [
      "spring",
      "summer",
      "fall",
      "winter"
    ],
    "rarity": "uncommon",
    "diet": "플랑크톤, 작은 갑각류",
    "animation_type": "swim_wiggle",
    "svg_id": "anglerfish",
    "source": "NOAA",
    "photo_url": "",
    "photo_credit": ""
  },
  {
    "id": "glass_squid",
    "name_ko": "유리오징어",
    "name_en": "Glass Squid",
    "scientific_name": "Cranchia scabra",
    "greeting_ko": "안녕! 나는 유리오징어야!",
    "greeting_en": "Hi! I'm a glass squid!",
    "greeting_revisit_ko": "또 봐서 반가워!",
    "description_ko": "내 몸은 투명해서 유리처럼 보여. 적들이 나를 못 봐. 큰 눈만 보이지!",
    "description_en": "I'm almost invisible like glass!",
    "fun_fact_ko": "유리오징어는 90% 이상이 투명해. 내장만 보이고 나머지는 안 보여!",
    "size_cm": 30,
    "depth_min": 200,
    "depth_max": 800,
    "zone": "twilight",
    "oceans": [
      "pacific",
      "atlantic",
      "indian"
    ],
    "seasons": [
      "spring",
      "summer",
      "fall",
      "winter"
    ],
    "rarity": "uncommon",
    "diet": "플랑크톤, 작은 물고기",
    "animation_type": "jet",
    "svg_id": "squid",
    "source": "NOAA",
    "photo_url": "",
    "photo_credit": ""
  },
  {
    "id": "comb_jellyfish",
    "name_ko": "빗해파리",
    "name_en": "Comb Jellyfish",
    "scientific_name": "Beroe cucumis",
    "greeting_ko": "안녕! 나는 빗해파리야!",
    "greeting_en": "Hi! I'm a comb jelly!",
    "greeting_revisit_ko": "또 만났구나!",
    "description_ko": "나는 무지개 빛을 내며 움직여. 빗처럼 생긴 섬모를 흔들어서 헤엄쳐. 정말 예뻐!",
    "description_en": "I shimmer with rainbow colors!",
    "fun_fact_ko": "빗해파리는 빛을 내지 않아. 섬모가 빛을 반사해서 무지개색으로 보여!",
    "size_cm": 15,
    "depth_min": 200,
    "depth_max": 1000,
    "zone": "twilight",
    "oceans": [
      "pacific",
      "atlantic",
      "indian",
      "arctic"
    ],
    "seasons": [
      "spring",
      "summer",
      "fall",
      "winter"
    ],
    "rarity": "common",
    "diet": "플랑크톤, 작은 해파리",
    "animation_type": "pulse",
    "svg_id": "jellyfish",
    "source": "NOAA",
    "photo_url": "",
    "photo_credit": ""
  },
  {
    "id": "deep_sea_jellyfish",
    "name_ko": "심해해파리",
    "name_en": "Deep Sea Jellyfish",
    "scientific_name": "Atolla wyvillei",
    "greeting_ko": "안녕! 나는 심해해파리야!",
    "greeting_en": "Hi! I'm a deep sea jelly!",
    "greeting_revisit_ko": "다시 만났네!",
    "description_ko": "나는 빨갛고 빛을 내. 위험하면 깜빡이며 빛을 내서 적을 놀라게 해!",
    "description_en": "I glow red and flash when scared!",
    "fun_fact_ko": "심해해파리는 '도둑 경보'를 켜. 깜빡이는 빛으로 큰 포식자를 불러서 적을 쫓아!",
    "size_cm": 20,
    "depth_min": 300,
    "depth_max": 1000,
    "zone": "twilight",
    "oceans": [
      "pacific",
      "atlantic",
      "indian"
    ],
    "seasons": [
      "spring",
      "summer",
      "fall",
      "winter"
    ],
    "rarity": "uncommon",
    "diet": "플랑크톤, 작은 갑각류",
    "animation_type": "pulse",
    "svg_id": "deep_sea_jellyfish",
    "source": "NOAA",
    "photo_url": "",
    "photo_credit": ""
  },
  {
    "id": "viperfish",
    "name_ko": "독사고기",
    "name_en": "Viperfish",
    "scientific_name": "Chauliodus sloani",
    "greeting_ko": "안녕! 나는 독사고기야!",
    "greeting_en": "Hi! I'm a viperfish!",
    "greeting_revisit_ko": "또 봐서 반가워!",
    "description_ko": "내 이빨은 길고 날카로워. 빛을 내서 먹이를 유인해. 무섭게 생겼지만 작아!",
    "description_en": "I have long sharp teeth!",
    "fun_fact_ko": "독사고기의 이빨은 너무 길어서 입을 닫을 수 없어. 입이 항상 열려있어!",
    "size_cm": 30,
    "depth_min": 250,
    "depth_max": 1000,
    "zone": "twilight",
    "oceans": [
      "pacific",
      "atlantic",
      "indian"
    ],
    "seasons": [
      "spring",
      "summer",
      "fall",
      "winter"
    ],
    "rarity": "uncommon",
    "diet": "작은 물고기, 갑각류",
    "animation_type": "swim_glide",
    "svg_id": "anglerfish",
    "source": "NOAA",
    "photo_url": "",
    "photo_credit": ""
  },
  {
    "id": "barreleye_fish",
    "name_ko": "주걱치",
    "name_en": "Barreleye Fish",
    "scientific_name": "Macropinna microstoma",
    "greeting_ko": "안녕! 나는 주걱치야!",
    "greeting_en": "Hi! I'm a barreleye!",
    "greeting_revisit_ko": "다시 만났구나!",
    "description_ko": "내 머리는 투명해! 안에 초록색 눈이 보여. 위를 보며 먹이를 찾아다녀.",
    "description_en": "My head is transparent with green eyes!",
    "fun_fact_ko": "주걱치의 눈은 머리 안에서 돌아가. 앞도 보고 위도 볼 수 있어!",
    "size_cm": 15,
    "depth_min": 400,
    "depth_max": 800,
    "zone": "twilight",
    "oceans": [
      "pacific"
    ],
    "seasons": [
      "spring",
      "summer",
      "fall",
      "winter"
    ],
    "rarity": "rare",
    "diet": "플랑크톤, 작은 해파리",
    "animation_type": "swim_glide",
    "svg_id": "anglerfish",
    "source": "NOAA",
    "photo_url": "",
    "photo_credit": ""
  },
  {
    "id": "pearl_oyster",
    "name_ko": "진주가이",
    "name_en": "Pearl Oyster",
    "scientific_name": "Pinctada margaritifera",
    "greeting_ko": "안녕! 나는 진주가이야!",
    "greeting_en": "Hi! I'm a pearl oyster!",
    "greeting_revisit_ko": "또 만났네!",
    "description_ko": "나는 진주를 만들어. 작은 모래가 들어오면 둘둥글게 감싸서 진주로 만들지!",
    "description_en": "I make beautiful pearls!",
    "fun_fact_ko": "진주는 수년간 조금씩 자라. 자개층을 쌓아서 반짝이는 진주가 돼!",
    "size_cm": 20,
    "depth_min": 200,
    "depth_max": 400,
    "zone": "twilight",
    "oceans": [
      "pacific",
      "indian"
    ],
    "seasons": [
      "spring",
      "summer",
      "fall",
      "winter"
    ],
    "rarity": "rare",
    "diet": "플랑크톤",
    "animation_type": "crawl",
    "svg_id": "shell",
    "source": "WoRMS",
    "photo_url": "",
    "photo_credit": ""
  },
  {
    "id": "deep_sea_shrimp",
    "name_ko": "심해가재",
    "name_en": "Deep Sea Shrimp",
    "scientific_name": "Acanthephyra purpurea",
    "greeting_ko": "안녕! 나는 심해가재야!",
    "greeting_en": "Hi! I'm a deep sea shrimp!",
    "greeting_revisit_ko": "또 봐서 반가워!",
    "description_ko": "나는 빨간색이야. 심해에선 빨간색이 보이지 않아서 투명한 것처럼 숨을 수 있어!",
    "description_en": "My red color is invisible in deep water!",
    "fun_fact_ko": "심해에는 빨간 빛이 없어. 빨간색은 검은색처럼 보여서 완벽한 위장이야!",
    "size_cm": 8,
    "depth_min": 300,
    "depth_max": 1000,
    "zone": "twilight",
    "oceans": [
      "pacific",
      "atlantic",
      "indian"
    ],
    "seasons": [
      "spring",
      "summer",
      "fall",
      "winter"
    ],
    "rarity": "common",
    "diet": "플랑크톤, 작은 생물",
    "animation_type": "swim_wiggle",
    "svg_id": "shrimp",
    "source": "NOAA",
    "photo_url": "",
    "photo_credit": ""
  },
  {
    "id": "lanternfish",
    "name_ko": "초롱이고기",
    "name_en": "Lanternfish",
    "scientific_name": "Myctophum punctatum",
    "greeting_ko": "안녕! 나는 초롱이고기야!",
    "greeting_en": "Hi! I'm a lanternfish!",
    "greeting_revisit_ko": "또 만났구나!",
    "description_ko": "내 몸에는 빛을 내는 점들이 있어. 반짝반짝 빛나며 헤엄쳐. 작지만 많아!",
    "description_en": "I have glowing dots all over my body!",
    "fun_fact_ko": "초롱이고기는 바다에서 가장 많은 물고기야. 전체 물고기의 절반이 넘어!",
    "size_cm": 10,
    "depth_min": 200,
    "depth_max": 1000,
    "zone": "twilight",
    "oceans": [
      "pacific",
      "atlantic",
      "indian"
    ],
    "seasons": [
      "spring",
      "summer",
      "fall",
      "winter"
    ],
    "rarity": "common",
    "diet": "플랑크톤, 작은 갑각류",
    "animation_type": "swim_wiggle",
    "svg_id": "anglerfish",
    "source": "NOAA",
    "photo_url": "",
    "photo_credit": ""
  },
  {
    "id": "dragonfish",
    "name_ko": "용고기",
    "name_en": "Black Dragonfish",
    "scientific_name": "Idiacanthus atlanticus",
    "greeting_ko": "안녕! 나는 용고기야!",
    "greeting_en": "Hi! I'm a dragonfish!",
    "greeting_revisit_ko": "다시 만나서 기뻐!",
    "description_ko": "나는 검고 길어. 턱 아래에 빛나는 수염이 있어. 빨간 빛을 내서 먹이를 몰래 봐!",
    "description_en": "I have a glowing barbel under my chin!",
    "fun_fact_ko": "용고기는 빨간 빛을 볼 수 있는 유일한 심해 물고기야. 다른 물고기는 못 봐!",
    "size_cm": 40,
    "depth_min": 200,
    "depth_max": 1000,
    "zone": "twilight",
    "oceans": [
      "pacific",
      "atlantic",
      "indian"
    ],
    "seasons": [
      "spring",
      "summer",
      "fall",
      "winter"
    ],
    "rarity": "uncommon",
    "diet": "작은 물고기, 갑각류",
    "animation_type": "swim_glide",
    "svg_id": "anglerfish",
    "source": "NOAA",
    "photo_url": "",
    "photo_credit": ""
  },
  {
    "id": "cookiecutter_shark",
    "name_ko": "쿠키커터상어",
    "name_en": "Cookiecutter Shark",
    "scientific_name": "Isistius brasiliensis",
    "greeting_ko": "안녕! 나는 쿠키커터상어야!",
    "greeting_en": "Hi! I'm a cookiecutter shark!",
    "greeting_revisit_ko": "또 봐서 반가워!",
    "description_ko": "나는 작지만 특별해. 큰 물고기에게 쿠키 모양으로 한 입씩 물어. 배에서 빛이 나!",
    "description_en": "I take cookie-shaped bites!",
    "fun_fact_ko": "쿠키커터상어는 잠수함에도 물어. 빛나는 배를 먹이로 착각해!",
    "size_cm": 50,
    "depth_min": 200,
    "depth_max": 1000,
    "zone": "twilight",
    "oceans": [
      "pacific",
      "atlantic"
    ],
    "seasons": [
      "spring",
      "summer",
      "fall",
      "winter"
    ],
    "rarity": "rare",
    "diet": "큰 물고기 살점",
    "animation_type": "swim_glide",
    "svg_id": "whale_shark",
    "source": "NOAA",
    "photo_url": "",
    "photo_credit": ""
  },
  {
    "id": "sperm_whale",
    "name_ko": "향유고래",
    "name_en": "Sperm Whale",
    "scientific_name": "Physeter macrocephalus",
    "greeting_ko": "안녕! 나는 향유고래야!",
    "greeting_en": "Hi! I'm a sperm whale!",
    "greeting_revisit_ko": "또 만났구나!",
    "description_ko": "나는 깊이 잠수해. 대왕오징어를 찾아 깊은 바다로 가. 큰 머리가 특징이야!",
    "description_en": "I dive deep to hunt giant squid!",
    "fun_fact_ko": "향유고래는 2시간 동안 숨을 참을 수 있어. 3000미터 깊이까지 잠수해!",
    "size_cm": 1600,
    "depth_min": 200,
    "depth_max": 1000,
    "zone": "twilight",
    "oceans": [
      "pacific",
      "atlantic",
      "indian"
    ],
    "seasons": [
      "spring",
      "summer",
      "fall",
      "winter"
    ],
    "rarity": "rare",
    "diet": "대왕오징어, 물고기",
    "animation_type": "swim_glide",
    "svg_id": "whale",
    "source": "NOAA",
    "photo_url": "",
    "photo_credit": ""
  },
  {
    "id": "siphonophore",
    "name_ko": "관해파리",
    "name_en": "Siphonophore",
    "scientific_name": "Apolemia uvaria",
    "greeting_ko": "안녕! 나는 관해파리야!",
    "greeting_en": "Hi! I'm a siphonophore!",
    "greeting_revisit_ko": "또 만났네!",
    "description_ko": "나는 작은 생물들이 모여서 하나처럼 살아. 길게 늘어져서 커튼처럼 보여!",
    "description_en": "Many tiny animals live together as one!",
    "fun_fact_ko": "관해파리는 40미터 이상 자라. 지구에서 가장 긴 동물 중 하나야!",
    "size_cm": 4000,
    "depth_min": 200,
    "depth_max": 1000,
    "zone": "twilight",
    "oceans": [
      "pacific",
      "atlantic",
      "indian"
    ],
    "seasons": [
      "spring",
      "summer",
      "fall",
      "winter"
    ],
    "rarity": "legendary",
    "diet": "플랑크톤, 작은 물고기",
    "animation_type": "float",
    "svg_id": "deep_sea_jellyfish",
    "source": "NOAA",
    "photo_url": "",
    "photo_credit": ""
  },
  {
    "id": "bigfin_squid",
    "name_ko": "긴팔오징어",
    "name_en": "Bigfin Squid",
    "scientific_name": "Magnapinna pacifica",
    "greeting_ko": "안녕! 나는 긴팔오징어야!",
    "greeting_en": "Hi! I'm a bigfin squid!",
    "greeting_revisit_ko": "다시 만났구나!",
    "description_ko": "내 팔은 정말 길어. 몸보다 20배 길 수도 있어. 팔을 늘어뜨리고 떠다녀!",
    "description_en": "My arms are incredibly long!",
    "fun_fact_ko": "긴팔오징어의 팔은 8미터까지 자라. 낚싯줄처럼 늘어뜨려서 먹이를 잡아!",
    "size_cm": 700,
    "depth_min": 400,
    "depth_max": 1000,
    "zone": "twilight",
    "oceans": [
      "pacific",
      "atlantic"
    ],
    "seasons": [
      "spring",
      "summer",
      "fall",
      "winter"
    ],
    "rarity": "legendary",
    "diet": "작은 갑각류, 물고기",
    "animation_type": "float",
    "svg_id": "giant_squid",
    "source": "NOAA",
    "photo_url": "",
    "photo_credit": ""
  },
  {
    "id": "stoplight_loosejaw",
    "name_ko": "신호등고기",
    "name_en": "Stoplight Loosejaw",
    "scientific_name": "Malacosteus niger",
    "greeting_ko": "안녕! 나는 신호등고기야!",
    "greeting_en": "Hi! I'm a stoplight loosejaw!",
    "greeting_revisit_ko": "또 봐서 반가워!",
    "description_ko": "나는 빨간 빛과 파란 빛을 내. 턱이 특별해서 크게 벌릴 수 있어!",
    "description_en": "I glow red and blue like a stoplight!",
    "fun_fact_ko": "신호등고기는 빨간 빛을 낼 수 있어. 이 빛으로 먹이를 몰래 찾아!",
    "size_cm": 25,
    "depth_min": 500,
    "depth_max": 1000,
    "zone": "twilight",
    "oceans": [
      "pacific",
      "atlantic"
    ],
    "seasons": [
      "spring",
      "summer",
      "fall",
      "winter"
    ],
    "rarity": "rare",
    "diet": "작은 물고기, 갑각류",
    "animation_type": "swim_glide",
    "svg_id": "anglerfish",
    "source": "NOAA",
    "photo_url": "",
    "photo_credit": ""
  },
  {
    "id": "gulper_eel",
    "name_ko": "주머니장어",
    "name_en": "Gulper Eel",
    "scientific_name": "Eurypharynx pelecanoides",
    "greeting_ko": "안녕! 나는 주머니장어야!",
    "greeting_en": "Hi! I'm a gulper eel!",
    "greeting_revisit_ko": "다시 만났구나!",
    "description_ko": "내 입은 정말 커! 나보다 큰 먹이도 삼킬 수 있어. 주머니처럼 입이 늘어나!",
    "description_en": "My mouth can open incredibly wide!",
    "fun_fact_ko": "주머니장어는 몸의 절반이 입이야. 위가 늘어나서 큰 먹이를 통째로 삼켜!",
    "size_cm": 80,
    "depth_min": 500,
    "depth_max": 1000,
    "zone": "twilight",
    "oceans": [
      "pacific",
      "atlantic",
      "indian"
    ],
    "seasons": [
      "spring",
      "summer",
      "fall",
      "winter"
    ],
    "rarity": "uncommon",
    "diet": "작은 물고기, 갑각류",
    "animation_type": "swim_glide",
    "svg_id": "anglerfish",
    "source": "NOAA",
    "photo_url": "",
    "photo_credit": ""
  },
  {
    "id": "sabertooth_fish",
    "name_ko": "검치고기",
    "name_en": "Sabertooth Fish",
    "scientific_name": "Coccorella atlantica",
    "greeting_ko": "안녕! 나는 검치고기야!",
    "greeting_en": "Hi! I'm a sabertooth fish!",
    "greeting_revisit_ko": "또 만났네!",
    "description_ko": "내 이빨은 길고 날카로워. 작지만 용감해. 나보다 큰 먹이도 잡아!",
    "description_en": "I have long sharp fangs!",
    "fun_fact_ko": "검치고기는 몸 크기에 비해 가장 긴 이빨을 가졌어. 입에 다 안 들어가!",
    "size_cm": 18,
    "depth_min": 400,
    "depth_max": 900,
    "zone": "twilight",
    "oceans": [
      "pacific",
      "atlantic"
    ],
    "seasons": [
      "spring",
      "summer",
      "fall",
      "winter"
    ],
    "rarity": "uncommon",
    "diet": "작은 물고기",
    "animation_type": "swim_wiggle",
    "svg_id": "anglerfish",
    "source": "NOAA",
    "photo_url": "",
    "photo_credit": ""
  },
  {
    "id": "telescope_octopus",
    "name_ko": "망원경문어",
    "name_en": "Telescope Octopus",
    "scientific_name": "Amphitretus pelagicus",
    "greeting_ko": "안녕! 나는 망원경문어야!",
    "greeting_en": "Hi! I'm a telescope octopus!",
    "greeting_revisit_ko": "다시 만나서 좋아!",
    "description_ko": "내 눈은 망원경처럼 생겼어. 투명한 몸에 큰 눈만 보여. 물 속을 둥둥 떠다녀!",
    "description_en": "My eyes look like telescopes!",
    "fun_fact_ko": "망원경문어의 눈은 몸 밖으로 튀어나와 있어. 360도를 다 볼 수 있어!",
    "size_cm": 20,
    "depth_min": 300,
    "depth_max": 800,
    "zone": "twilight",
    "oceans": [
      "pacific"
    ],
    "seasons": [
      "spring",
      "summer",
      "fall",
      "winter"
    ],
    "rarity": "rare",
    "diet": "작은 갑각류, 물고기",
    "animation_type": "jet",
    "svg_id": "octopus",
    "source": "NOAA",
    "photo_url": "",
    "photo_credit": ""
  },
  {
    "id": "chambered_nautilus",
    "name_ko": "방울앵무조개",
    "name_en": "Chambered Nautilus",
    "scientific_name": "Nautilus belauensis",
    "greeting_ko": "안녕! 나는 방울앵무조개야!",
    "greeting_en": "Hi! I'm a chambered nautilus!",
    "greeting_revisit_ko": "또 만났구나!",
    "description_ko": "나는 앵무조개 친척이야. 껍데기 안에 방이 많아. 가스로 깊이를 조절해!",
    "description_en": "I have many chambers in my shell!",
    "fun_fact_ko": "방울앵무조개는 최대 90개의 팔을 가졌어. 다른 두족류보다 훨씬 많아!",
    "size_cm": 18,
    "depth_min": 200,
    "depth_max": 600,
    "zone": "twilight",
    "oceans": [
      "pacific",
      "indian"
    ],
    "seasons": [
      "spring",
      "summer",
      "fall",
      "winter"
    ],
    "rarity": "rare",
    "diet": "작은 갑각류, 물고기",
    "animation_type": "jet",
    "svg_id": "shell",
    "source": "NOAA",
    "photo_url": "",
    "photo_credit": ""
  },
  {
    "id": "bristlemouth",
    "name_ko": "강모입고기",
    "name_en": "Bristlemouth",
    "scientific_name": "Cyclothone microdon",
    "greeting_ko": "안녕! 나는 강모입고기야!",
    "greeting_en": "Hi! I'm a bristlemouth!",
    "greeting_revisit_ko": "또 만났구나! 반가워!",
    "description_ko": "나는 아주 작고 투명해. 하지만 바다에서 가장 많은 물고기야. 엄청 많이 있어!",
    "description_en": "I'm the most common fish in the ocean!",
    "fun_fact_ko": "강모입고기는 지구에서 가장 많은 척추동물이야. 수조 마리가 바다에 살아!",
    "size_cm": 5,
    "depth_min": 200,
    "depth_max": 1000,
    "zone": "twilight",
    "oceans": [
      "pacific",
      "atlantic",
      "indian"
    ],
    "seasons": [
      "spring",
      "summer",
      "fall",
      "winter"
    ],
    "rarity": "common",
    "diet": "플랑크톤, 작은 갑각류",
    "animation_type": "swim_wiggle",
    "svg_id": "anglerfish",
    "source": "FishBase",
    "photo_url": "",
    "photo_credit": ""
  },
  {
    "id": "firefly_squid",
    "name_ko": "반딧불오징어",
    "name_en": "Firefly Squid",
    "scientific_name": "Watasenia scintillans",
    "greeting_ko": "안녕! 나는 반딧불오징어야!",
    "greeting_en": "Hi! I'm a firefly squid!",
    "greeting_revisit_ko": "또 만나서 기뻐!",
    "description_ko": "내 몸 전체에서 파란 빛이 나! 반딧불이처럼 반짝반짝 빛나며 헤엄쳐.",
    "description_en": "My whole body glows blue like fireflies!",
    "fun_fact_ko": "반딧불오징어는 매년 봄 일본 바다에서 수백만 마리가 모여 빛의 쇼를 해!",
    "size_cm": 8,
    "depth_min": 200,
    "depth_max": 600,
    "zone": "twilight",
    "oceans": [
      "pacific"
    ],
    "seasons": [
      "spring",
      "summer"
    ],
    "rarity": "common",
    "diet": "플랑크톤, 작은 물고기",
    "animation_type": "jet",
    "svg_id": "squid",
    "source": "FishBase",
    "photo_url": "",
    "photo_credit": ""
  },
  {
    "id": "tomopteris",
    "name_ko": "유영갯지렁이",
    "name_en": "Tomopteris",
    "scientific_name": "Tomopteris helgolandica",
    "greeting_ko": "안녕! 나는 유영갯지렁이야!",
    "greeting_en": "Hi! I'm a tomopteris worm!",
    "greeting_revisit_ko": "다시 만났네! 반가워!",
    "description_ko": "나는 투명하고 노란 빛을 내. 바다에서 헤엄치는 지렁이야. 날개처럼 생긴 다리가 있어!",
    "description_en": "I'm a transparent swimming worm that glows yellow!",
    "fun_fact_ko": "유영갯지렁이는 노란색 빛을 내는 희귀한 생물이야. 대부분은 파란색을 내거든!",
    "size_cm": 5,
    "depth_min": 200,
    "depth_max": 800,
    "zone": "twilight",
    "oceans": [
      "pacific",
      "atlantic",
      "indian"
    ],
    "seasons": [
      "spring",
      "summer",
      "fall",
      "winter"
    ],
    "rarity": "common",
    "diet": "플랑크톤",
    "animation_type": "swim_wiggle",
    "svg_id": "eel",
    "source": "WoRMS",
    "photo_url": "",
    "photo_credit": ""
  },
  {
    "id": "slickhead",
    "name_ko": "미끈머리고기",
    "name_en": "Slickhead",
    "scientific_name": "Alepocephalus bairdii",
    "greeting_ko": "안녕! 나는 미끈머리고기야!",
    "greeting_en": "Hi! I'm a slickhead!",
    "greeting_revisit_ko": "또 만났구나!",
    "description_ko": "내 머리는 반질반질해. 비늘이 없는 매끄러운 머리가 특징이야. 느긋하게 헤엄쳐!",
    "description_en": "My head is smooth and slippery!",
    "fun_fact_ko": "미끈머리고기는 머리에 비늘이 전혀 없어. 미끄러워서 이런 이름이 됐어!",
    "size_cm": 60,
    "depth_min": 400,
    "depth_max": 1000,
    "zone": "twilight",
    "oceans": [
      "atlantic",
      "pacific"
    ],
    "seasons": [
      "spring",
      "summer",
      "fall",
      "winter"
    ],
    "rarity": "common",
    "diet": "해파리, 플랑크톤",
    "animation_type": "swim_glide",
    "svg_id": "generic_fish",
    "source": "FishBase",
    "photo_url": "",
    "photo_credit": ""
  },
  {
    "id": "giant_ostracod",
    "name_ko": "거대패충류",
    "name_en": "Giant Ostracod",
    "scientific_name": "Gigantocypris muelleri",
    "greeting_ko": "안녕! 나는 거대패충류야!",
    "greeting_en": "Hi! I'm a giant ostracod!",
    "greeting_revisit_ko": "다시 만났네!",
    "description_ko": "나는 동그란 껍데기 안에 사는 작은 갑각류야. 큰 반사 눈으로 빛을 모아!",
    "description_en": "I'm a tiny crustacean with mirror-like eyes!",
    "fun_fact_ko": "거대패충류의 눈은 거울처럼 빛을 모아. 어둠 속에서도 잘 볼 수 있어!",
    "size_cm": 3,
    "depth_min": 200,
    "depth_max": 1000,
    "zone": "twilight",
    "oceans": [
      "pacific",
      "atlantic",
      "indian"
    ],
    "seasons": [
      "spring",
      "summer",
      "fall",
      "winter"
    ],
    "rarity": "common",
    "diet": "플랑크톤, 작은 생물",
    "animation_type": "float",
    "svg_id": "shrimp",
    "source": "WoRMS",
    "photo_url": "",
    "photo_credit": ""
  },
  {
    "id": "midwater_jellyfish",
    "name_ko": "중층해파리",
    "name_en": "Midwater Jellyfish",
    "scientific_name": "Solmissus marshalli",
    "greeting_ko": "안녕! 나는 중층해파리야!",
    "greeting_en": "Hi! I'm a midwater jellyfish!",
    "greeting_revisit_ko": "또 봐서 반가워!",
    "description_ko": "나는 투명한 해파리야. 조용히 떠다니며 촉수로 먹이를 잡아. 유령처럼 보여!",
    "description_en": "I'm a transparent ghost-like jelly!",
    "fun_fact_ko": "중층해파리는 너무 투명해서 카메라로 찍기 어려워. 유령해파리라고도 불러!",
    "size_cm": 15,
    "depth_min": 200,
    "depth_max": 800,
    "zone": "twilight",
    "oceans": [
      "pacific",
      "atlantic"
    ],
    "seasons": [
      "spring",
      "summer",
      "fall",
      "winter"
    ],
    "rarity": "common",
    "diet": "플랑크톤, 작은 갑각류",
    "animation_type": "pulse",
    "svg_id": "jellyfish",
    "source": "NOAA",
    "photo_url": "",
    "photo_credit": ""
  },
  {
    "id": "deep_sea_anglerfish",
    "name_ko": "심해아귀",
    "name_en": "Deep Sea Anglerfish",
    "scientific_name": "Melanocetus johnsonii",
    "greeting_ko": "안녕! 나는 심해아귀야!",
    "greeting_en": "Hi! I'm a deep sea anglerfish!",
    "greeting_revisit_ko": "또 만났구나!",
    "description_ko": "내 머리에 빛나는 낚싯대가 있어. 빛으로 물고기를 유인해서 잡아먹어!",
    "description_en": "I have a glowing lure on my head!",
    "fun_fact_ko": "심해아귀 수컷은 아주 작아서 암컷 몸에 붙어서 평생 살아. 신기하지?",
    "size_cm": 18,
    "depth_min": 300,
    "depth_max": 1000,
    "zone": "twilight",
    "oceans": [
      "pacific",
      "atlantic",
      "indian"
    ],
    "seasons": [
      "spring",
      "summer",
      "fall",
      "winter"
    ],
    "rarity": "common",
    "diet": "작은 물고기, 갑각류",
    "animation_type": "float",
    "svg_id": "anglerfish",
    "source": "NOAA",
    "photo_url": "",
    "photo_credit": ""
  },
  {
    "id": "pelagic_sea_cucumber",
    "name_ko": "부유해삼",
    "name_en": "Pelagic Sea Cucumber",
    "scientific_name": "Enypniastes eximia",
    "greeting_ko": "안녕! 나는 부유해삼이야!",
    "greeting_en": "Hi! I'm a swimming sea cucumber!",
    "greeting_revisit_ko": "다시 만났네! 반가워!",
    "description_ko": "나는 헤엄치는 해삼이야! 투명한 몸으로 물 속을 떠다녀. 바닥이 아닌 물 속에 살아!",
    "description_en": "I'm a sea cucumber that can swim!",
    "fun_fact_ko": "부유해삼은 투명해서 먹은 음식이 그대로 보여. 헤드라이트 같은 별명이 있어!",
    "size_cm": 25,
    "depth_min": 500,
    "depth_max": 1000,
    "zone": "twilight",
    "oceans": [
      "pacific",
      "atlantic"
    ],
    "seasons": [
      "spring",
      "summer",
      "fall",
      "winter"
    ],
    "rarity": "common",
    "diet": "바닥 퇴적물, 플랑크톤",
    "animation_type": "float",
    "svg_id": "sea_cucumber",
    "source": "NOAA",
    "photo_url": "",
    "photo_credit": ""
  },
  {
    "id": "deep_sea_salp",
    "name_ko": "심해살프",
    "name_en": "Deep Sea Salp",
    "scientific_name": "Salpa maxima",
    "greeting_ko": "안녕! 나는 심해살프야!",
    "greeting_en": "Hi! I'm a deep sea salp!",
    "greeting_revisit_ko": "또 만나서 좋아!",
    "description_ko": "나는 투명한 통 모양이야. 물을 들이마시고 내뱉으며 이동해. 젤리처럼 말랑해!",
    "description_en": "I'm a transparent barrel that pumps water!",
    "fun_fact_ko": "살프는 몸으로 물을 빨아들여서 제트 추진처럼 이동해. 로켓 같아!",
    "size_cm": 20,
    "depth_min": 200,
    "depth_max": 800,
    "zone": "twilight",
    "oceans": [
      "pacific",
      "atlantic",
      "indian",
      "antarctic"
    ],
    "seasons": [
      "spring",
      "summer",
      "fall",
      "winter"
    ],
    "rarity": "common",
    "diet": "플랑크톤",
    "animation_type": "pulse",
    "svg_id": "jellyfish",
    "source": "WoRMS",
    "photo_url": "",
    "photo_credit": ""
  },
  {
    "id": "marine_hatchetfish",
    "name_ko": "은도끼고기",
    "name_en": "Silver Hatchetfish",
    "scientific_name": "Sternoptyx diaphana",
    "greeting_ko": "안녕! 나는 은도끼고기야!",
    "greeting_en": "Hi! I'm a silver hatchetfish!",
    "greeting_revisit_ko": "또 봐서 반가워!",
    "description_ko": "나는 은색으로 반짝여. 도끼 모양 몸에 배 쪽에서 빛이 나서 그림자를 숨겨!",
    "description_en": "I'm a shiny silver fish shaped like a hatchet!",
    "fun_fact_ko": "은도끼고기는 배 빛으로 위장해. 위에서 보면 바다 빛과 같아서 안 보여!",
    "size_cm": 7,
    "depth_min": 200,
    "depth_max": 700,
    "zone": "twilight",
    "oceans": [
      "pacific",
      "atlantic",
      "indian"
    ],
    "seasons": [
      "spring",
      "summer",
      "fall",
      "winter"
    ],
    "rarity": "common",
    "diet": "플랑크톤, 작은 갑각류",
    "animation_type": "swim_wiggle",
    "svg_id": "anglerfish",
    "source": "FishBase",
    "photo_url": "",
    "photo_credit": ""
  },
  {
    "id": "pyrosome",
    "name_ko": "불꽃벌레",
    "name_en": "Pyrosome",
    "scientific_name": "Pyrosoma atlanticum",
    "greeting_ko": "안녕! 나는 불꽃벌레야!",
    "greeting_en": "Hi! I'm a pyrosome!",
    "greeting_revisit_ko": "다시 만났구나!",
    "description_ko": "나는 수천 마리가 모여 긴 통 모양을 만들어. 만지면 파란 빛이 번져 나가!",
    "description_en": "Thousands of tiny animals form my tube-shaped body!",
    "fun_fact_ko": "불꽃벌레를 건드리면 빛이 파도처럼 퍼져나가. 이름도 '불의 몸'이란 뜻이야!",
    "size_cm": 300,
    "depth_min": 200,
    "depth_max": 800,
    "zone": "twilight",
    "oceans": [
      "pacific",
      "atlantic",
      "indian"
    ],
    "seasons": [
      "spring",
      "summer",
      "fall",
      "winter"
    ],
    "rarity": "common",
    "diet": "플랑크톤",
    "animation_type": "float",
    "svg_id": "jellyfish",
    "source": "WoRMS",
    "photo_url": "",
    "photo_credit": ""
  },
  {
    "id": "pacific_viperfish",
    "name_ko": "태평양독사고기",
    "name_en": "Pacific Viperfish",
    "scientific_name": "Chauliodus macouni",
    "greeting_ko": "안녕! 나는 태평양독사고기야!",
    "greeting_en": "Hi! I'm a Pacific viperfish!",
    "greeting_revisit_ko": "또 만났네!",
    "description_ko": "나는 태평양에 사는 독사고기야. 길고 날카로운 이빨과 빛나는 몸이 특징이야!",
    "description_en": "I have fangs and a glowing body!",
    "fun_fact_ko": "태평양독사고기는 밤에 수면 가까이 올라와. 낮에는 깊은 곳에 숨어 있어!",
    "size_cm": 25,
    "depth_min": 200,
    "depth_max": 1000,
    "zone": "twilight",
    "oceans": [
      "pacific"
    ],
    "seasons": [
      "spring",
      "summer",
      "fall",
      "winter"
    ],
    "rarity": "common",
    "diet": "작은 물고기, 갑각류",
    "animation_type": "swim_glide",
    "svg_id": "anglerfish",
    "source": "FishBase",
    "photo_url": "",
    "photo_credit": ""
  },
  {
    "id": "orange_roughy",
    "name_ko": "오렌지러피",
    "name_en": "Orange Roughy",
    "scientific_name": "Hoplostethus atlanticus",
    "greeting_ko": "안녕! 나는 오렌지러피야!",
    "greeting_en": "Hi! I'm an orange roughy!",
    "greeting_revisit_ko": "또 만나서 기뻐!",
    "description_ko": "나는 주황색 물고기야. 아주 천천히 자라지만 정말 오래 살아. 느긋한 성격이야!",
    "description_en": "I'm an orange fish that lives very long!",
    "fun_fact_ko": "오렌지러피는 150살 넘게 살 수 있어. 할아버지의 할아버지보다 오래 사는 거야!",
    "size_cm": 50,
    "depth_min": 400,
    "depth_max": 1000,
    "zone": "twilight",
    "oceans": [
      "pacific",
      "atlantic",
      "indian"
    ],
    "seasons": [
      "spring",
      "summer",
      "fall",
      "winter"
    ],
    "rarity": "uncommon",
    "diet": "작은 물고기, 오징어",
    "animation_type": "swim_glide",
    "svg_id": "generic_fish",
    "source": "FishBase",
    "photo_url": "",
    "photo_credit": ""
  },
  {
    "id": "sixgill_shark",
    "name_ko": "육조상어",
    "name_en": "Bluntnose Sixgill Shark",
    "scientific_name": "Hexanchus griseus",
    "greeting_ko": "안녕! 나는 육조상어야!",
    "greeting_en": "Hi! I'm a sixgill shark!",
    "greeting_revisit_ko": "다시 만났구나!",
    "description_ko": "나는 아가미가 6개야! 보통 상어는 5개인데 나는 하나 더 많아. 크고 느긋해!",
    "description_en": "I have six gills instead of the usual five!",
    "fun_fact_ko": "육조상어는 공룡 시대부터 살아온 고대 상어야. 2억 년 전 모습 그대로야!",
    "size_cm": 500,
    "depth_min": 200,
    "depth_max": 1000,
    "zone": "twilight",
    "oceans": [
      "pacific",
      "atlantic",
      "indian"
    ],
    "seasons": [
      "spring",
      "summer",
      "fall",
      "winter"
    ],
    "rarity": "uncommon",
    "diet": "물고기, 오징어, 갑각류",
    "animation_type": "swim_glide",
    "svg_id": "whale_shark",
    "source": "FishBase",
    "photo_url": "",
    "photo_credit": ""
  },
  {
    "id": "crystal_jellyfish",
    "name_ko": "수정해파리",
    "name_en": "Crystal Jellyfish",
    "scientific_name": "Aequorea victoria",
    "greeting_ko": "안녕! 나는 수정해파리야!",
    "greeting_en": "Hi! I'm a crystal jellyfish!",
    "greeting_revisit_ko": "또 봐서 반가워!",
    "description_ko": "나는 투명하고 초록빛을 내. 과학자들이 내 빛으로 노벨상을 받았어! 정말 특별하지?",
    "description_en": "My green glow helped scientists win a Nobel Prize!",
    "fun_fact_ko": "수정해파리의 형광 단백질은 과학 실험에 많이 써. 노벨 화학상도 받았어!",
    "size_cm": 25,
    "depth_min": 200,
    "depth_max": 600,
    "zone": "twilight",
    "oceans": [
      "pacific"
    ],
    "seasons": [
      "spring",
      "summer",
      "fall"
    ],
    "rarity": "uncommon",
    "diet": "플랑크톤, 작은 갑각류",
    "animation_type": "pulse",
    "svg_id": "jellyfish",
    "source": "NOAA",
    "photo_url": "",
    "photo_credit": ""
  },
  {
    "id": "bramble_shark",
    "name_ko": "가시상어",
    "name_en": "Bramble Shark",
    "scientific_name": "Echinorhinus brucus",
    "greeting_ko": "안녕! 나는 가시상어야!",
    "greeting_en": "Hi! I'm a bramble shark!",
    "greeting_revisit_ko": "다시 만났네!",
    "description_ko": "내 피부에는 가시 같은 돌기가 있어. 장미 가시처럼 생겨서 가시상어라 불려!",
    "description_en": "My skin is covered in thorn-like bumps!",
    "fun_fact_ko": "가시상어의 피부 돌기는 진짜 이빨과 같은 구조야. 온몸이 이빨인 셈이야!",
    "size_cm": 300,
    "depth_min": 200,
    "depth_max": 900,
    "zone": "twilight",
    "oceans": [
      "atlantic",
      "indian",
      "pacific"
    ],
    "seasons": [
      "spring",
      "summer",
      "fall",
      "winter"
    ],
    "rarity": "uncommon",
    "diet": "물고기, 오징어, 게",
    "animation_type": "swim_glide",
    "svg_id": "whale_shark",
    "source": "FishBase",
    "photo_url": "",
    "photo_credit": ""
  },
  {
    "id": "velvet_belly_lanternshark",
    "name_ko": "벨벳배상어",
    "name_en": "Velvet Belly Lanternshark",
    "scientific_name": "Etmopterus spinax",
    "greeting_ko": "안녕! 나는 벨벳배상어야!",
    "greeting_en": "Hi! I'm a velvet belly lanternshark!",
    "greeting_revisit_ko": "또 만났구나!",
    "description_ko": "내 배는 부드러운 벨벳처럼 생겼어. 배에서 빛이 나서 아래쪽 적에게 안 보여!",
    "description_en": "My belly glows to hide from predators below!",
    "fun_fact_ko": "벨벳배상어는 빛나는 상어야. 배의 빛으로 위에서 오는 빛과 섞여 숨어!",
    "size_cm": 45,
    "depth_min": 200,
    "depth_max": 800,
    "zone": "twilight",
    "oceans": [
      "atlantic"
    ],
    "seasons": [
      "spring",
      "summer",
      "fall",
      "winter"
    ],
    "rarity": "uncommon",
    "diet": "작은 물고기, 오징어",
    "animation_type": "swim_glide",
    "svg_id": "whale_shark",
    "source": "FishBase",
    "photo_url": "",
    "photo_credit": ""
  },
  {
    "id": "splendid_alfonsino",
    "name_ko": "금눈돔",
    "name_en": "Splendid Alfonsino",
    "scientific_name": "Beryx splendens",
    "greeting_ko": "안녕! 나는 금눈돔이야!",
    "greeting_en": "Hi! I'm a splendid alfonsino!",
    "greeting_revisit_ko": "또 봐서 반가워!",
    "description_ko": "내 눈은 크고 금색으로 빛나. 빨간 몸에 큰 눈이 정말 멋져. 맛도 좋아!",
    "description_en": "I have big golden eyes and a red body!",
    "fun_fact_ko": "금눈돔은 어두운 바다에서 큰 눈으로 빛을 모아. 고양이 눈처럼 잘 보여!",
    "size_cm": 50,
    "depth_min": 200,
    "depth_max": 800,
    "zone": "twilight",
    "oceans": [
      "pacific",
      "atlantic",
      "indian"
    ],
    "seasons": [
      "spring",
      "summer",
      "fall",
      "winter"
    ],
    "rarity": "uncommon",
    "diet": "작은 물고기, 갑각류",
    "animation_type": "swim_glide",
    "svg_id": "generic_fish",
    "source": "FishBase",
    "photo_url": "",
    "photo_credit": ""
  },
  {
    "id": "jewel_squid",
    "name_ko": "보석오징어",
    "name_en": "Jewel Squid",
    "scientific_name": "Histioteuthis bonnellii",
    "greeting_ko": "안녕! 나는 보석오징어야!",
    "greeting_en": "Hi! I'm a jewel squid!",
    "greeting_revisit_ko": "다시 만나서 좋아!",
    "description_ko": "내 몸에는 보석처럼 빛나는 점들이 있어. 두 눈의 크기가 달라서 재미있어!",
    "description_en": "I have jewel-like glowing spots and mismatched eyes!",
    "fun_fact_ko": "보석오징어는 한쪽 눈이 다른 쪽보다 2배나 커. 위아래를 따로 봐!",
    "size_cm": 20,
    "depth_min": 300,
    "depth_max": 900,
    "zone": "twilight",
    "oceans": [
      "atlantic",
      "pacific"
    ],
    "seasons": [
      "spring",
      "summer",
      "fall",
      "winter"
    ],
    "rarity": "uncommon",
    "diet": "작은 물고기, 갑각류",
    "animation_type": "jet",
    "svg_id": "squid",
    "source": "WoRMS",
    "photo_url": "",
    "photo_credit": ""
  },
  {
    "id": "cockatoo_squid",
    "name_ko": "앵무오징어",
    "name_en": "Cockatoo Squid",
    "scientific_name": "Galiteuthis glacialis",
    "greeting_ko": "안녕! 나는 앵무오징어야!",
    "greeting_en": "Hi! I'm a cockatoo squid!",
    "greeting_revisit_ko": "또 만났구나!",
    "description_ko": "나는 투명하고 앵무새 볏 같은 지느러미가 있어. 남극 바다에서도 살 수 있어!",
    "description_en": "I have a crest like a cockatoo parrot!",
    "fun_fact_ko": "앵무오징어는 차가운 남극 바다에서도 살아. 투명한 몸이 얼음처럼 보여!",
    "size_cm": 40,
    "depth_min": 300,
    "depth_max": 1000,
    "zone": "twilight",
    "oceans": [
      "antarctic",
      "pacific",
      "atlantic"
    ],
    "seasons": [
      "spring",
      "summer",
      "fall",
      "winter"
    ],
    "rarity": "uncommon",
    "diet": "작은 물고기, 갑각류",
    "animation_type": "jet",
    "svg_id": "squid",
    "source": "WoRMS",
    "photo_url": "",
    "photo_credit": ""
  },
  {
    "id": "bloodybelly_comb_jelly",
    "name_ko": "붉은빗해파리",
    "name_en": "Bloodybelly Comb Jelly",
    "scientific_name": "Lampocteis cruentiventer",
    "greeting_ko": "안녕! 나는 붉은빗해파리야!",
    "greeting_en": "Hi! I'm a bloodybelly comb jelly!",
    "greeting_revisit_ko": "다시 만났네!",
    "description_ko": "내 배는 새빨간색이야. 섬모가 무지개빛으로 반짝이면서 빨간 배가 빛나!",
    "description_en": "My red belly shimmers with rainbow light!",
    "fun_fact_ko": "붉은빗해파리의 빨간 배는 먹은 먹이의 빛을 숨겨줘. 완벽한 위장술이야!",
    "size_cm": 15,
    "depth_min": 300,
    "depth_max": 1000,
    "zone": "twilight",
    "oceans": [
      "pacific"
    ],
    "seasons": [
      "spring",
      "summer",
      "fall",
      "winter"
    ],
    "rarity": "uncommon",
    "diet": "플랑크톤, 작은 해파리",
    "animation_type": "pulse",
    "svg_id": "jellyfish",
    "source": "NOAA",
    "photo_url": "",
    "photo_credit": ""
  },
  {
    "id": "greeneye_fish",
    "name_ko": "녹안고기",
    "name_en": "Greeneye Fish",
    "scientific_name": "Chlorophthalmus agassizi",
    "greeting_ko": "안녕! 나는 녹안고기야!",
    "greeting_en": "Hi! I'm a greeneye fish!",
    "greeting_revisit_ko": "또 봐서 반가워!",
    "description_ko": "내 눈은 초록색으로 빛나. 어두운 바다에서 초록 눈이 반짝이며 먹이를 찾아!",
    "description_en": "My eyes glow bright green in the dark!",
    "fun_fact_ko": "녹안고기의 눈은 특별한 층이 있어서 초록색으로 빛나. 야간 투시경 같아!",
    "size_cm": 30,
    "depth_min": 200,
    "depth_max": 700,
    "zone": "twilight",
    "oceans": [
      "atlantic",
      "pacific"
    ],
    "seasons": [
      "spring",
      "summer",
      "fall",
      "winter"
    ],
    "rarity": "uncommon",
    "diet": "작은 갑각류, 물고기",
    "animation_type": "swim_glide",
    "svg_id": "generic_fish",
    "source": "FishBase",
    "photo_url": "",
    "photo_credit": ""
  },
  {
    "id": "owlfish",
    "name_ko": "올빼미고기",
    "name_en": "Owlfish",
    "scientific_name": "Ipnops murrayi",
    "greeting_ko": "안녕! 나는 올빼미고기야!",
    "greeting_en": "Hi! I'm an owlfish!",
    "greeting_revisit_ko": "다시 만났구나!",
    "description_ko": "내 머리 위에 넓적한 눈이 있어. 올빼미처럼 생긴 눈으로 위쪽 빛을 감지해!",
    "description_en": "I have flat eyes on top of my head like an owl!",
    "fun_fact_ko": "올빼미고기의 눈은 렌즈가 없어. 대신 넓은 면으로 약한 빛도 감지해!",
    "size_cm": 15,
    "depth_min": 500,
    "depth_max": 1000,
    "zone": "twilight",
    "oceans": [
      "atlantic",
      "pacific",
      "indian"
    ],
    "seasons": [
      "spring",
      "summer",
      "fall",
      "winter"
    ],
    "rarity": "uncommon",
    "diet": "바닥 생물, 갑각류",
    "animation_type": "crawl",
    "svg_id": "generic_fish",
    "source": "FishBase",
    "photo_url": "",
    "photo_credit": ""
  },
  {
    "id": "chiroteuthis",
    "name_ko": "긴팔꼴뚜기",
    "name_en": "Long-armed Squid",
    "scientific_name": "Chiroteuthis veranyi",
    "greeting_ko": "안녕! 나는 긴팔꼴뚜기야!",
    "greeting_en": "Hi! I'm a long-armed squid!",
    "greeting_revisit_ko": "또 만났네!",
    "description_ko": "내 촉수는 정말 길어. 투명한 몸에 길고 가는 팔을 늘어뜨리고 떠다녀!",
    "description_en": "My tentacles are incredibly long and thin!",
    "fun_fact_ko": "긴팔꼴뚜기의 팔은 몸 길이의 10배야. 낚시줄처럼 내려서 먹이를 잡아!",
    "size_cm": 35,
    "depth_min": 300,
    "depth_max": 900,
    "zone": "twilight",
    "oceans": [
      "atlantic",
      "pacific"
    ],
    "seasons": [
      "spring",
      "summer",
      "fall",
      "winter"
    ],
    "rarity": "uncommon",
    "diet": "작은 갑각류, 물고기",
    "animation_type": "float",
    "svg_id": "squid",
    "source": "WoRMS",
    "photo_url": "",
    "photo_credit": ""
  },
  {
    "id": "atolla_jellyfish",
    "name_ko": "아톨라해파리",
    "name_en": "Atolla Jellyfish",
    "scientific_name": "Atolla vanhoeffeni",
    "greeting_ko": "안녕! 나는 아톨라해파리야!",
    "greeting_en": "Hi! I'm an atolla jellyfish!",
    "greeting_revisit_ko": "또 만나서 좋아!",
    "description_ko": "나는 왕관처럼 생긴 해파리야. 위험하면 파란 빛을 빙글빙글 돌려서 경보를 울려!",
    "description_en": "I spin blue light like an alarm when scared!",
    "fun_fact_ko": "아톨라해파리는 '바다의 비상벨'이야. 빙글빙글 도는 빛으로 큰 동물을 불러!",
    "size_cm": 15,
    "depth_min": 400,
    "depth_max": 1000,
    "zone": "twilight",
    "oceans": [
      "pacific",
      "atlantic",
      "indian",
      "arctic"
    ],
    "seasons": [
      "spring",
      "summer",
      "fall",
      "winter"
    ],
    "rarity": "uncommon",
    "diet": "플랑크톤, 작은 갑각류",
    "animation_type": "pulse",
    "svg_id": "deep_sea_jellyfish",
    "source": "NOAA",
    "photo_url": "",
    "photo_credit": ""
  },
  {
    "id": "giant_amphipod",
    "name_ko": "거대단각류",
    "name_en": "Giant Amphipod",
    "scientific_name": "Alicella gigantea",
    "greeting_ko": "안녕! 나는 거대단각류야!",
    "greeting_en": "Hi! I'm a giant amphipod!",
    "greeting_revisit_ko": "다시 만났네! 반가워!",
    "description_ko": "나는 새우를 닮은 거대한 갑각류야. 깊은 바다에서 커다랗게 자라. 청소부 역할을 해!",
    "description_en": "I'm a giant shrimp-like deep sea cleaner!",
    "fun_fact_ko": "거대단각류는 심해의 청소부야. 가라앉는 먹이를 먹어서 바다를 깨끗하게 해!",
    "size_cm": 30,
    "depth_min": 500,
    "depth_max": 1000,
    "zone": "twilight",
    "oceans": [
      "pacific",
      "atlantic"
    ],
    "seasons": [
      "spring",
      "summer",
      "fall",
      "winter"
    ],
    "rarity": "rare",
    "diet": "가라앉는 유기물, 죽은 생물",
    "animation_type": "swim_wiggle",
    "svg_id": "crab",
    "source": "WoRMS",
    "photo_url": "",
    "photo_credit": ""
  },
  {
    "id": "deep_sea_medusa",
    "name_ko": "심해메두사",
    "name_en": "Deep Sea Medusa",
    "scientific_name": "Deepstaria enigmatica",
    "greeting_ko": "안녕! 나는 심해메두사야!",
    "greeting_en": "Hi! I'm a deep sea medusa!",
    "greeting_revisit_ko": "또 봐서 반가워!",
    "description_ko": "나는 커다란 봉지처럼 생긴 해파리야. 몸을 넓게 펼쳐서 먹이를 감싸 잡아!",
    "description_en": "I look like a giant bag that catches prey!",
    "fun_fact_ko": "심해메두사는 비닐봉지처럼 보여. 몸을 부풀려 먹이를 통째로 감싸버려!",
    "size_cm": 60,
    "depth_min": 600,
    "depth_max": 1000,
    "zone": "twilight",
    "oceans": [
      "pacific",
      "atlantic"
    ],
    "seasons": [
      "spring",
      "summer",
      "fall",
      "winter"
    ],
    "rarity": "rare",
    "diet": "작은 갑각류, 해파리",
    "animation_type": "pulse",
    "svg_id": "deep_sea_jellyfish",
    "source": "NOAA",
    "photo_url": "",
    "photo_credit": ""
  },
  {
    "id": "ocean_sunfish",
    "name_ko": "개복치",
    "name_en": "Ocean Sunfish",
    "scientific_name": "Mola mola",
    "greeting_ko": "안녕! 나는 개복치야!",
    "greeting_en": "Hi! I'm an ocean sunfish!",
    "greeting_revisit_ko": "다시 만나서 기뻐!",
    "description_ko": "나는 둥글고 납작해. 세상에서 가장 무거운 뼈물고기야. 해파리를 좋아해!",
    "description_en": "I'm the world's heaviest bony fish!",
    "fun_fact_ko": "개복치는 2톤까지 자라. 알을 3억 개나 낳는 기록을 가지고 있어!",
    "size_cm": 300,
    "depth_min": 200,
    "depth_max": 600,
    "zone": "twilight",
    "oceans": [
      "pacific",
      "atlantic",
      "indian"
    ],
    "seasons": [
      "spring",
      "summer",
      "fall"
    ],
    "rarity": "rare",
    "diet": "해파리, 플랑크톤",
    "animation_type": "swim_glide",
    "svg_id": "pufferfish",
    "source": "FishBase",
    "photo_url": "",
    "photo_credit": ""
  },
  {
    "id": "oarfish",
    "name_ko": "산갈치",
    "name_en": "Giant Oarfish",
    "scientific_name": "Regalecus glesne",
    "greeting_ko": "안녕! 나는 산갈치야!",
    "greeting_en": "Hi! I'm a giant oarfish!",
    "greeting_revisit_ko": "또 만났구나! 놀랍지?",
    "description_ko": "나는 세상에서 가장 긴 뼈물고기야. 은빛 몸에 빨간 지느러미가 멋져. 바다뱀 전설의 주인공이야!",
    "description_en": "I'm the longest bony fish in the world!",
    "fun_fact_ko": "산갈치는 11미터까지 자라. 바다뱀이나 용 전설의 원인이 됐어!",
    "size_cm": 1100,
    "depth_min": 200,
    "depth_max": 1000,
    "zone": "twilight",
    "oceans": [
      "pacific",
      "atlantic",
      "indian"
    ],
    "seasons": [
      "spring",
      "summer",
      "fall",
      "winter"
    ],
    "rarity": "legendary",
    "diet": "플랑크톤, 작은 갑각류",
    "animation_type": "swim_glide",
    "svg_id": "eel",
    "source": "FishBase",
    "photo_url": "",
    "photo_credit": ""
  },
  {
    "id": "giant_isopod",
    "name_ko": "거대등각류",
    "name_en": "Giant Isopod",
    "scientific_name": "Bathynomus giganteus",
    "greeting_ko": "안녕! 나는 거대등각류야!",
    "greeting_en": "Hi! I'm a giant isopod!",
    "greeting_revisit_ko": "다시 만나서 좋아!",
    "description_ko": "나는 공벌레의 거대한 친척이야. 동그랗게 말릴 수 있어. 심해의 청소부로 불려!",
    "description_en": "I'm a giant deep-sea relative of the pill bug!",
    "fun_fact_ko": "거대등각류는 5년 넘게 안 먹어도 살아. 먹이가 드문 심해에서 생존 비결이야!",
    "size_cm": 40,
    "depth_min": 300,
    "depth_max": 1000,
    "zone": "twilight",
    "oceans": [
      "pacific",
      "atlantic",
      "indian"
    ],
    "seasons": [
      "spring",
      "summer",
      "fall",
      "winter"
    ],
    "rarity": "legendary",
    "diet": "가라앉는 유기물, 죽은 생물",
    "animation_type": "crawl",
    "svg_id": "crab",
    "source": "NOAA",
    "photo_url": "",
    "photo_credit": ""
  }
]
